spey_pyhf/__init__.py
spey_pyhf/_version.py
spey_pyhf/data.py
spey_pyhf/helper_functions.py
spey_pyhf/interface.py
spey_pyhf/manager.py
spey_pyhf/simplify.py
spey_pyhf/utils.py
spey_pyhf-0.2.0.dist-info/LICENSE
spey_pyhf-0.2.0.dist-info/METADATA
spey_pyhf-0.2.0.dist-info/WHEEL
spey_pyhf-0.2.0.dist-info/entry_points.txt
spey_pyhf-0.2.0.dist-info/top_level.txt
spey_pyhf-0.2.0.dist-info/RECORD
