Metadata-Version: 2.1
Name: spey-pyhf
Version: 0.2.0
Summary: pyhf plugin for spey interface
Home-page: https://github.com/SpeysideHEP/spey-pyhf
Download-URL: https://github.com/SpeysideHEP/spey-pyhf/archive/refs/tags/v0.2.0.tar.gz
Author: Jack Y. Araz
Author-email: jack.araz@stonybrook.edu
License: MIT
Project-URL: Bug Tracker, https://github.com/SpeysideHEP/spey-pyhf/issues
Project-URL: Documentation, https://spey-pyhf.readthedocs.io
Project-URL: Repository, https://github.com/SpeysideHEP/spey-pyhf
Project-URL: Homepage, https://github.com/SpeysideHEP/spey-pyhf
Project-URL: Download, https://github.com/SpeysideHEP/spey-pyhf/archive/refs/tags/v0.2.0.tar.gz
Classifier: Intended Audience :: Science/Research
Classifier: License :: OSI Approved :: MIT License
Classifier: Operating System :: OS Independent
Classifier: Topic :: Scientific/Engineering :: Physics
Classifier: Programming Language :: Python
Classifier: Programming Language :: Python :: 3
Classifier: Programming Language :: Python :: 3.8
Classifier: Programming Language :: Python :: 3.9
Classifier: Programming Language :: Python :: 3.10
Classifier: Programming Language :: Python :: 3.11
Classifier: Programming Language :: Python :: 3.12
Requires-Python: >=3.8, <3.13
License-File: LICENSE
Requires-Dist: pyhf ==0.7.6
Requires-Dist: spey >=0.2.1
Provides-Extra: dev
Requires-Dist: pytest-cov >=3.0.0 ; extra == 'dev'
Requires-Dist: pytest >=7.1.2 ; extra == 'dev'
Requires-Dist: twine >=3.7.1 ; extra == 'dev'
Requires-Dist: wheel >=0.37.1 ; extra == 'dev'
Provides-Extra: doc
Requires-Dist: myst-parser ; extra == 'doc'
Requires-Dist: nbsphinx !=0.8.8 ; extra == 'doc'
Requires-Dist: sphinx-click ; extra == 'doc'
Requires-Dist: sphinx-copybutton >=0.3.2 ; extra == 'doc'
Requires-Dist: sphinx-issues ; extra == 'doc'
Requires-Dist: sphinx-rtd-size ; extra == 'doc'
Requires-Dist: sphinx-togglebutton >=0.3.0 ; extra == 'doc'
Requires-Dist: sphinx ==6.2.1 ; extra == 'doc'
Requires-Dist: sphinx-rtd-theme ; extra == 'doc'
Requires-Dist: sphinxcontrib-bibtex ~=2.1 ; extra == 'doc'
Provides-Extra: jax
Requires-Dist: jax >=0.3.35 ; extra == 'jax'
